MANIFEST.in
README.rst
setup.cfg
setup.py
PyCosmo/Background.py
PyCosmo/Cosmo.py
PyCosmo/CosmologyCore.ipynb
PyCosmo/LinearPerturbationApprox.py
PyCosmo/LinearPerturbationBase.py
PyCosmo/LinearPerturbationTable.py
PyCosmo/NonLinearPerturbationHaloFit.py
PyCosmo/NonLinearPerturbationMead.py
PyCosmo/NonLinearPerturbationTable.py
PyCosmo/Obs.py
PyCosmo/PerturbationBase.py
PyCosmo/Projection.py
PyCosmo/TheoryPredTables.py
PyCosmo/_Cosmics.py
PyCosmo/_Ctable.py
PyCosmo/_Plotting.py
PyCosmo/_Recombination.py
PyCosmo/_RecombinationClass.py
PyCosmo/_RecombinationCosmics.py
PyCosmo/_RedshiftDistribution.py
PyCosmo/_Tables.py
PyCosmo/_Util.py
PyCosmo/__init__.py
PyCosmo/_cache_utils.py
PyCosmo/_derivs_boltz_hope.py
PyCosmo/_scipy_utils.py
PyCosmo/_structs.py
PyCosmo/_sympy_helpers.py
PyCosmo/compute_fields.py
PyCosmo/load_configs.py
PyCosmo/patches.py
PyCosmo/symbols.py
PyCosmo/v2_config.py
PyCosmo/code_generators/__init__.py
PyCosmo/code_generators/build_gsl.py
PyCosmo/code_generators/create_curry_class.py
PyCosmo/code_generators/sympy_to_c_compiler.py
PyCosmo/config/__init__.py
PyCosmo/config/default.py
PyCosmo/config/default_temp.py
PyCosmo/config/default_v2.py
PyCosmo/cython/__init__.py
PyCosmo/cython/const.c
PyCosmo/cython/constf.c
PyCosmo/cython/halo_integral.c
PyCosmo/cython/halo_integral.pyx
PyCosmo/cython/logf.c
PyCosmo/cython/main.c
PyCosmo/cython/mconf.h
PyCosmo/cython/mtherr.c
PyCosmo/cython/polevl.c
PyCosmo/cython/polevlf.c
PyCosmo/cython/protos.h
PyCosmo/cython/sici.c
PyCosmo/cython/sici.h
PyCosmo/cython/sici32.c
PyCosmo/cython/sicif.c
PyCosmo/cython/sinf.c
PyCosmoLite.egg-info/PKG-INFO
PyCosmoLite.egg-info/SOURCES.txt
PyCosmoLite.egg-info/dependency_links.txt
PyCosmoLite.egg-info/entry_points.txt
PyCosmoLite.egg-info/requires.txt
PyCosmoLite.egg-info/top_level.txt