Metadata-Version: 1.1
Name: PyCosmoLite
Version: 0.4.3
Summary: A multi-purpose cosmology calculation tool
Home-page: http://cosmo-docs.phys.ethz.ch/PyCosmo
Author: Adam Amara
Author-email: adam.amara@phys.ethz.ch
License: MIT License
Platform: UNKNOWN
Classifier: Development Status :: 4 - Beta
Classifier: Intended Audience :: Science/Research
Classifier: License :: OSI Approved :: MIT License
Classifier: Natural Language :: English
Classifier: Operating System :: OS Independent
Classifier: Programming Language :: Python
Classifier: Programming Language :: C
Classifier: Topic :: Scientific/Engineering :: Astronomy
Classifier: Programming Language :: Python :: 2
Classifier: Programming Language :: Python :: 2.6
Classifier: Programming Language :: Python :: 2.7
